plastidUtilis/AbnormalDetect.py
plastidUtilis/BLAST.py
plastidUtilis/Filter.py
plastidUtilis/Longest.py
plastidUtilis/SequenceAppend.py
plastidUtilis/Sort.py
plastidUtilis/Stats.py
plastidUtilis/Table2GBK.py
plastidUtilis/Translate.py
plastidUtilis-0.0.5.dist-info/LICENSE
plastidUtilis-0.0.5.dist-info/METADATA
plastidUtilis-0.0.5.dist-info/WHEEL
plastidUtilis-0.0.5.dist-info/top_level.txt
plastidUtilis-0.0.5.dist-info/RECORD
