Metadata-Version: 2.1
Name: plastidUtilis
Version: 0.0.5
Summary: chloroplast/mitochondrion annotation toolkits
Author-email: Youpu Chen <otis.hongpu@gmail.com>
Classifier: Development Status :: 3 - Alpha
Classifier: Intended Audience :: Information Technology
Classifier: Topic :: Scientific/Engineering :: Bio-Informatics
Classifier: License :: OSI Approved :: MIT License
Classifier: Programming Language :: Python :: 3
Classifier: Programming Language :: Python :: 3.8
Requires-Python: >=3.8
License-File: LICENSE
Requires-Dist: biopython
